momotou/__init__.py
momotou/rua.py
momotou/data/1.png
momotou/data/10.png
momotou/data/2.png
momotou/data/3.png
momotou/data/4.png
momotou/data/5.png
momotou/data/6.png
momotou/data/7.png
momotou/data/8.png
momotou/data/9.png
momotou-1.0.2.dist-info/METADATA
momotou-1.0.2.dist-info/WHEEL
momotou-1.0.2.dist-info/top_level.txt
momotou-1.0.2.dist-info/RECORD
