Metadata-Version: 2.1
Name: momotou
Version: 1.0.2
Summary: 摸摸头表情包制作
Home-page: https://www.qsnctf.com/
Author: Moxin
Author-email: 1044631097@qq.com
Requires-Dist: Pillow
